odoo/addons/hr_expense_analytic_require/README.rst
odoo/addons/hr_expense_analytic_require/__init__.py
odoo/addons/hr_expense_analytic_require/__manifest__.py
odoo/addons/hr_expense_analytic_require/data/res_company_data.xml
odoo/addons/hr_expense_analytic_require/i18n/hr_expense_analytic_require.pot
odoo/addons/hr_expense_analytic_require/i18n/it.po
odoo/addons/hr_expense_analytic_require/models/__init__.py
odoo/addons/hr_expense_analytic_require/models/company.py
odoo/addons/hr_expense_analytic_require/models/hr_expense.py
odoo/addons/hr_expense_analytic_require/models/res_config_settings.py
odoo/addons/hr_expense_analytic_require/readme/CONFIGURE.rst
odoo/addons/hr_expense_analytic_require/readme/CONTRIBUTORS.rst
odoo/addons/hr_expense_analytic_require/readme/DESCRIPTION.rst
odoo/addons/hr_expense_analytic_require/readme/USAGE.rst
odoo/addons/hr_expense_analytic_require/static/description/icon.png
odoo/addons/hr_expense_analytic_require/static/description/index.html
odoo/addons/hr_expense_analytic_require/views/hr_expense_views.xml
odoo/addons/hr_expense_analytic_require/views/res_company_view.xml
odoo/addons/hr_expense_analytic_require/views/res_config_settings_views.xml
odoo12_addon_hr_expense_analytic_require-12.0.1.0.0.99.dev10.dist-info/METADATA
odoo12_addon_hr_expense_analytic_require-12.0.1.0.0.99.dev10.dist-info/WHEEL
odoo12_addon_hr_expense_analytic_require-12.0.1.0.0.99.dev10.dist-info/top_level.txt
odoo12_addon_hr_expense_analytic_require-12.0.1.0.0.99.dev10.dist-info/RECORD
